smsru/__init__.py
smsru/admin.py
smsru/apps.py
smsru/models.py
smsru/service.py
smsru/signals.py
smsru/tests.py
smsru/urls.py
smsru/views.py
smsru/locale/ru/LC_MESSAGES/django.mo
smsru/locale/ru/LC_MESSAGES/django.po
smsru/management/__init__.py
smsru/management/commands/__init__.py
smsru/management/commands/send-sms-ru.py
smsru/migrations/0001_initial.py
smsru/migrations/0002_fix_log.py
smsru/migrations/__init__.py
django_smsru-1.0.4.dist-info/LICENSE
django_smsru-1.0.4.dist-info/METADATA
django_smsru-1.0.4.dist-info/WHEEL
django_smsru-1.0.4.dist-info/top_level.txt
django_smsru-1.0.4.dist-info/RECORD
